fc_skx_bigdate.py
fc_skx-2.0.dist-info/METADATA
fc_skx-2.0.dist-info/WHEEL
fc_skx-2.0.dist-info/top_level.txt
fc_skx-2.0.dist-info/RECORD
