Metadata-Version: 2.1
Name: fc-skx
Version: 2.0
Summary: 这个包里只有name和cs
Home-page: UNKNOWN
Author: skx
Author-email: 1802628079@qq.com
License: UNKNOWN
Platform: UNKNOWN
